<NFe xmlns="http://www.portalfiscal.inf.br/nfe"><infNFe versao="2.00" Id="NFe35120700762956000120550010000017691826176424"><ide><cUF>35</cUF><cNF>82617642</cNF><natOp>VENDA DE PRODUCAO DO ESTABELECIMENTO</natOp><indPag>1</indPag><mod>55</mod><serie>1</serie><nNF>1769</nNF><dEmi>2012-07-01</dEmi><dSaiEnt>2012-07-02</dSaiEnt><hSaiEnt>09:47:14</hSaiEnt><tpNF>1</tpNF><cMunFG>3501608</cMunFG><tpImp>1</tpImp><tpEmis>1</tpEmis><cDV>4</cDV><tpAmb>1</tpAmb><finNFe>1</finNFe><procEmi>0</procEmi><verProc>2.70</verProc></ide><emit><CNPJ>00762956000120</CNPJ><xNome>DOTTER DO BRASIL LTDA</xNome><xFant>DIGITAL HOLOGRAM</xFant><enderEmit><xLgr>Rua CABO OSWALDO DE MORAES</xLgr><nro>377</nro><xBairro>VILA RASMUSSEM</xBairro><cMun>3501608</cMun><xMun>Americana</xMun><UF>SP</UF><CEP>13466030</CEP><cPais>1058</cPais><xPais>Brasil</xPais><fone>1934627611</fone></enderEmit><IE>165343525111</IE><IM>73228</IM><CNAE>1822100</CNAE><CRT>1</CRT></emit><dest><CNPJ>34164319000506</CNPJ><xNome>CASA DA MOEDA DO BRASIL CMB</xNome><enderDest><xLgr>Rua Rene Bittencourt</xLgr><nro>371</nro><xBairro>Dist. Ind. Sta Cruz</xBairro><cMun>3304557</cMun><xMun>Rio de Janeiro</xMun><UF>RJ</UF><CEP>23565200</CEP><cPais>1058</cPais><xPais>Brasil</xPais><fone>2124142158</fone></enderDest><IE>82346988</IE><email>nfe@cmb.gov.br</email></dest><det nItem="1"><prod><cProd>54</cProd><cEAN></cEAN><xProd>Substrato de Poliester Auto-Adesivo Anti-Click</xProd><NCM>39199000</NCM><CFOP>6101</CFOP><uCom>FL</uCom><qCom>200250.0000</qCom><vUnCom>11.5200000000</vUnCom><vProd>2306880.00</vProd><cEANTrib></cEANTrib><uTrib>FL</uTrib><qTrib>200250.0000</qTrib><vUnTrib>11.5200000000</vUnTrib><indTot>1</indTot></prod><imposto><ICMS><ICMSSN101><orig>0</orig><CSOSN>101</CSOSN><pCredSN>2.82</pCredSN><vCredICMSSN>65054.02</vCredICMSSN></ICMSSN101></ICMS><IPI><cEnq>999</cEnq><IPITrib><CST>99</CST><vBC>0.00</vBC><pIPI>0.00</pIPI><vIPI>0.00</vIPI></IPITrib></IPI><II><vBC>0.00</vBC><vDespAdu>0.00</vDespAdu><vII>0.00</vII><vIOF>0.00</vIOF></II><PIS><PISOutr><CST>99</CST><vBC>0.00</vBC><pPIS>0.00</pPIS><vPIS>0.00</vPIS></PISOutr></PIS><COFINS><COFINSOutr><CST>99</CST><vBC>0.00</vBC><pCOFINS>0.00</pCOFINS><vCOFINS>0.00</vCOFINS></COFINSOutr></COFINS></imposto></det><total><ICMSTot><vBC>0.00</vBC><vICMS>0.00</vICMS><vBCST>0.00</vBCST><vST>0.00</vST><vProd>2306880.00</vProd><vFrete>0.00</vFrete><vSeg>0.00</vSeg><vDesc>0.00</vDesc><vII>0.00</vII><vIPI>0.00</vIPI><vPIS>0.00</vPIS><vCOFINS>0.00</vCOFINS><vOutro>0.00</vOutro><vNF>2306880.00</vNF></ICMSTot></total><transp><modFrete>0</modFrete><transporta><CNPJ>04601873000100</CNPJ><xNome>TRANS-FERRARI TRANSPORTE E LOGISTICA LTDA -EPP</xNome><IE>675162936119</IE><xEnder>ESTAcAO  BENEDITO CESARIO DE OLIVEIRA, 100 - BAIRRO VILA IAS</xEnder><xMun>TABOAO DA SERRA</xMun><UF>SP</UF></transporta><veicTransp><placa>DVT3767</placa><UF>SP</UF></veicTransp><vol><qVol>801</qVol><esp>PACOTES</esp><nVol>0</nVol><pesoL>10153.000</pesoL><pesoB>11414.250</pesoB></vol></transp><cobr><fat><nFat>1769</nFat><vOrig>2306880.00</vOrig><vLiq>2306880.00</vLiq></fat><dup><nDup>001769/AA</nDup><dVenc>2012-08-02</dVenc><vDup>2306880.00</vDup></dup></cobr><infAdic><infCpl>PERMITE O APROVEITAMENTO DO CREDITO DE ICMS NO VALOR DE R$ 65.054,02 CORRESPONDENTE A ALIQUOTA DE 2,82%, NOS TERMOS DO ART. 23 DA LC 123 DOCUMENTO EMITIDO POR EMPRESA OPTANTE PELO SIMPLES NACIONAL CONFORME LEI COMPLEMENTAR No. 123/2006 RESOLUCAO CGSN No. 10 ART 2o. INCISO I LOCAL DE CARGA: BRAGANCA PAULISTA / SP LOCAL DE DESCARGA: RIO DE JANEIRO / RJ 200.250 Folhas embaladas em 801 pacotes, em 20 paletes. 19 paletes com 40 pacotes e 01 palete com 41 pacotes. Codigo CMB: 300520 FAX DEGER No. FG 092 Lote de Fabricacao: 06/2012</infCpl></infAdic><exporta><UFEmbarq>SP</UFEmbarq><xLocEmbarq>BRAGANCA PAULISTA</xLocEmbarq></exporta></infNFe></NFe>